{"noiseKey":{"private":{"type":"Buffer","data":"0PFhGf97g8ZKXZRmcnDHls2YvrFfVJboEbgrvmW5oX8="},"public":{"type":"Buffer","data":"S2ThZ4v7NaBX40+ad63ZUDTkXTxxvVX6XPvC5LHOX38="}},"pairingEphemeralKeyPair":{"private":{"type":"Buffer","data":"sGTXeB2lZPMHZdIlUj61MaurT1DU79Zo2kP+fwRAcWo="},"public":{"type":"Buffer","data":"F7PWXNjRUsirnSEEeHRNkWJvYACM6ik3RieBWndAJkE="}},"signedIdentityKey":{"private":{"type":"Buffer","data":"SMJ8Hk8uQZQfEc/vLgJDqU3Kq65RMffQid3TGNfdI08="},"public":{"type":"Buffer","data":"F5inRh6fOfgCbeej3ICYb6f/TlY5i4t/quelVxW3OBw="}},"signedPreKey":{"keyPair":{"private":{"type":"Buffer","data":"0N/7mkZSkXbwho9PqaauOnhmBQy5E09J8I6y5fGMSlI="},"public":{"type":"Buffer","data":"b5spbsowL5IX+XQdbpsQQ8twp5kmk0znbk2vjhn/XW8="}},"signature":{"type":"Buffer","data":"tmFb/2IcoWVe7/xirE9JZuXp1ul/U4BTNDD+9Yj2es2mo5/2tjX9+39ftLKANhtlrS1PuT/qqpZJLb+kTPRDCA=="},"keyId":1},"registrationId":68,"advSecretKey":"qaN50myHcVZJewrCsziisKeV8K9HTEAYDPcePunGHMw=","processedHistoryMessages":[{"key":{"remoteJid":"923242209093@s.whatsapp.net","fromMe":true,"id":"ACF03AC839EE935C7AEA182604B460B3"},"messageTimestamp":1758187660},{"key":{"remoteJid":"923242209093@s.whatsapp.net","fromMe":true,"id":"ACF95ECE4B0EAC5F583C2E4469E942AB"},"messageTimestamp":1758187668},{"key":{"remoteJid":"923242209093@s.whatsapp.net","fromMe":true,"id":"AC78FBC82C9947F0F01A36FFED87FAB7"},"messageTimestamp":1758187881},{"key":{"remoteJid":"923242209093@s.whatsapp.net","fromMe":true,"id":"ACFB6C8A2CAF02D05850ADCDAE7494EC"},"messageTimestamp":1758188150},{"key":{"remoteJid":"923242209093@s.whatsapp.net","fromMe":true,"id":"ACFB6C8A2CAF02D05850ADCDAE7494EC"},"messageTimestamp":1758188150},{"key":{"remoteJid":"923242209093@s.whatsapp.net","fromMe":true,"id":"AC41A9AA6C04040E2767F8F89F47560F"},"messageTimestamp":1758188188},{"key":{"remoteJid":"923242209093@s.whatsapp.net","fromMe":true,"id":"AC28BF22FE73EDBEE00A7284CDA0902D"},"messageTimestamp":1758188213},{"key":{"remoteJid":"923242209093@s.whatsapp.net","fromMe":true,"id":"AC5E0D802DC13A9C0ECDB2D524D87624"},"messageTimestamp":1758188232},{"key":{"remoteJid":"923242209093@s.whatsapp.net","fromMe":true,"id":"AC4BC24B7F683577AF5753057E91C1C8"},"messageTimestamp":1758188260},{"key":{"remoteJid":"923242209093@s.whatsapp.net","fromMe":true,"id":"AC0F39AAD8BBD9B9C10A3F4362F37EDD"},"messageTimestamp":1758188329},{"key":{"remoteJid":"923242209093@s.whatsapp.net","fromMe":true,"id":"AC836AFE40AB528CAC08D4A7C2CF58C3"},"messageTimestamp":1758188341},{"key":{"remoteJid":"923242209093@s.whatsapp.net","fromMe":true,"id":"AC633261874AC1F46CF24823DECF8591"},"messageTimestamp":1758188357},{"key":{"remoteJid":"923242209093@s.whatsapp.net","fromMe":true,"id":"ACADD2CD07FC20589B295AB3FB8D84CF"},"messageTimestamp":1758188365},{"key":{"remoteJid":"923242209093@s.whatsapp.net","fromMe":true,"id":"AC0D633EF8CCD8290A53B9994AB8909B"},"messageTimestamp":1758188391},{"key":{"remoteJid":"923242209093@s.whatsapp.net","fromMe":true,"id":"ACB9D1BE8ED504B148FA16B601168428"},"messageTimestamp":1758188508},{"key":{"remoteJid":"923242209093@s.whatsapp.net","fromMe":true,"id":"AC40F87DEB493B8E1F81B64AAE91BB19"},"messageTimestamp":1758188511},{"key":{"remoteJid":"923242209093@s.whatsapp.net","fromMe":true,"id":"AC3805693BD0715387962BB5F4AC7D27"},"messageTimestamp":1758188511},{"key":{"remoteJid":"923242209093@s.whatsapp.net","fromMe":true,"id":"AC7DD838428E606CAE70929B7E93DB36"},"messageTimestamp":1758188549},{"key":{"remoteJid":"923242209093@s.whatsapp.net","fromMe":true,"id":"AC3905BC6FCBD9E7F3984A9C8E1EDAC8"},"messageTimestamp":1758188550}],"nextPreKeyId":565,"firstUnuploadedPreKeyId":565,"accountSyncCounter":1,"accountSettings":{"unarchiveChats":false},"deviceId":"l0HEyxmqRuqnrv4h666QSQ","phoneId":"b0be09e3-e0eb-4b81-af04-578654bb980a","identityId":{"type":"Buffer","data":"10jz5JFzA2NlXAmRIfgwVjrlgY0="},"registered":true,"backupToken":{"type":"Buffer","data":"Gw2+ngNXR0rFgY3FZwqvrkPG+ys="},"registration":{},"pairingCode":"3LPDV8Y2","me":{"id":"923242209093:61@s.whatsapp.net","lid":"260739109527696:61@lid","name":"•ＳＡＤ ＬＯＶＥＲ•"},"account":{"details":"CJCso6YGEOqgr8YGGAEgACgA","accountSignatureKey":"71WJSSRlcyBQcesqw2e13OWGWm8sVuNxazeYmtjYfwQ=","accountSignature":"kyuq9XiBs8JOJ524xat0Pedg4ObMEjBzPKJQ+acEavMcKZ844j5NkRi3+8pUe2pUtCD2Kgz7kJfEvAow+oj5AQ==","deviceSignature":"79T8OKxeNEVU3EHXY0Jyls/BvVQmbd+fCcebHKW27m1YnjxD/Tc6Nrl4n3fmkCHq59DbqRefD9KvFtRTjn9lCQ=="},"signalIdentities":[{"identifier":{"name":"923242209093:61@s.whatsapp.net","deviceId":0},"identifierKey":{"type":"Buffer","data":"Be9ViUkkZXMgUHHrKsNntdzlhlpvLFbjcWs3mJrY2H8E"}}],"platform":"android","routingInfo":{"type":"Buffer","data":"CA0IBQ=="},"lastAccountSyncTimestamp":1758187640,"lastPropHash":"1K4hH4","myAppStateKeyId":"AAAAAOvi"}